leiting_sms_sdk.py
leiting_sms_sdk-1.0.1.dist-info/licenses/LICENSE
leiting_sms_sdk-1.0.1.dist-info/METADATA
leiting_sms_sdk-1.0.1.dist-info/WHEEL
leiting_sms_sdk-1.0.1.dist-info/top_level.txt
leiting_sms_sdk-1.0.1.dist-info/RECORD
