Metadata-Version: 2.4
Name: leiting-sms-sdk
Version: 1.0.1
Summary: 雷霆短信验证码服务 Python SDK
Home-page: https://github.com/yourusername/leiting-sms-sdk
Author: Your Name
Author-email: Your Name <your.email@example.com>
License: MIT
Project-URL: Homepage, https://github.com/yourusername/leiting-sms-sdk
Project-URL: Bug Reports, https://github.com/yourusername/leiting-sms-sdk/issues
Project-URL: Source, https://github.com/yourusername/leiting-sms-sdk
Project-URL: Documentation, https://github.com/yourusername/leiting-sms-sdk#readme
Keywords: sms,verification,code,leiting,短信,验证码,雷霆
Classifier: Development Status :: 5 - Production/Stable
Classifier: Intended Audience :: Developers
Classifier: License :: OSI Approved :: MIT License
Classifier: Operating System :: OS Independent
Classifier: Programming Language :: Python :: 3
Classifier: Programming Language :: Python :: 3.7
Classifier: Programming Language :: Python :: 3.8
Classifier: Programming Language :: Python :: 3.9
Classifier: Programming Language :: Python :: 3.10
Classifier: Programming Language :: Python :: 3.11
Classifier: Programming Language :: Python :: 3.12
Classifier: Topic :: Communications
Classifier: Topic :: Internet :: WWW/HTTP
Classifier: Topic :: Software Development :: Libraries :: Python Modules
Classifier: Topic :: System :: Networking
Requires-Python: >=3.7
License-File: LICENSE
Requires-Dist: requests>=2.25.0
Dynamic: author
Dynamic: home-page
Dynamic: license-file
Dynamic: requires-python
